{
  "$schema": "http://json.schemastore.org/sarif-1.0.0",
  "version": "1.0.0",
  "runs": [
    {
      "tool": {
        "name": "Microsoft (R) Visual C# Compiler",
        "version": "4.6.0.0",
        "fileVersion": "4.6.0-3.23259.8 (c3cc1d0c)",
        "semanticVersion": "4.6.0",
        "language": "en-IT"
      },
      "results": [
        {
          "ruleId": "CS8613",
          "level": "warning",
          "message": "Nullability of reference types in return type of 'Task<Session> UserRepository.AddSession(Session session)' doesn't match implicitly implemented member 'Task<Session?> IUserRepository.AddSession(Session session)'.",
          "locations": [
            {
              "resultFile": {
                "uri": "file:///Users/abdulhadi.elhussain/Projects/AbdulhadiNagarroAssignment/AbdulhadiNagarroAssignment.Infrastructure/Persistence/Repositories/UserRepository.cs",
                "region": {
                  "startLine": 13,
                  "startColumn": 36,
                  "endLine": 13,
                  "endColumn": 46
                }
              }
            }
          ],
          "properties": {
            "warningLevel": 1
          }
        },
        {
          "ruleId": "CS8634",
          "level": "warning",
          "message": "The type 'AbdulhadiNagarroAssignment.Domain.Models.Role?' cannot be used as type parameter 'TEntity' in the generic type or method 'DbSet<TEntity>'. Nullability of type argument 'AbdulhadiNagarroAssignment.Domain.Models.Role?' doesn't match 'class' constraint.",
          "locations": [
            {
              "resultFile": {
                "uri": "file:///Users/abdulhadi.elhussain/Projects/AbdulhadiNagarroAssignment/AbdulhadiNagarroAssignment.Infrastructure/Persistence/AccountsManagerContext.cs",
                "region": {
                  "startLine": 21,
                  "startColumn": 29,
                  "endLine": 21,
                  "endColumn": 34
                }
              }
            }
          ],
          "properties": {
            "warningLevel": 1
          }
        },
        {
          "ruleId": "CS8634",
          "level": "warning",
          "message": "The type 'AbdulhadiNagarroAssignment.Domain.Models.User?' cannot be used as type parameter 'TEntity' in the generic type or method 'DbSet<TEntity>'. Nullability of type argument 'AbdulhadiNagarroAssignment.Domain.Models.User?' doesn't match 'class' constraint.",
          "locations": [
            {
              "resultFile": {
                "uri": "file:///Users/abdulhadi.elhussain/Projects/AbdulhadiNagarroAssignment/AbdulhadiNagarroAssignment.Infrastructure/Persistence/AccountsManagerContext.cs",
                "region": {
                  "startLine": 22,
                  "startColumn": 29,
                  "endLine": 22,
                  "endColumn": 34
                }
              }
            }
          ],
          "properties": {
            "warningLevel": 1
          }
        },
        {
          "ruleId": "CS8634",
          "level": "warning",
          "message": "The type 'AbdulhadiNagarroAssignment.Domain.Models.UserRole?' cannot be used as type parameter 'TEntity' in the generic type or method 'DbSet<TEntity>'. Nullability of type argument 'AbdulhadiNagarroAssignment.Domain.Models.UserRole?' doesn't match 'class' constraint.",
          "locations": [
            {
              "resultFile": {
                "uri": "file:///Users/abdulhadi.elhussain/Projects/AbdulhadiNagarroAssignment/AbdulhadiNagarroAssignment.Infrastructure/Persistence/AccountsManagerContext.cs",
                "region": {
                  "startLine": 23,
                  "startColumn": 33,
                  "endLine": 23,
                  "endColumn": 43
                }
              }
            }
          ],
          "properties": {
            "warningLevel": 1
          }
        },
        {
          "ruleId": "CS8634",
          "level": "warning",
          "message": "The type 'AbdulhadiNagarroAssignment.Domain.Models.Session?' cannot be used as type parameter 'TEntity' in the generic type or method 'DbSet<TEntity>'. Nullability of type argument 'AbdulhadiNagarroAssignment.Domain.Models.Session?' doesn't match 'class' constraint.",
          "locations": [
            {
              "resultFile": {
                "uri": "file:///Users/abdulhadi.elhussain/Projects/AbdulhadiNagarroAssignment/AbdulhadiNagarroAssignment.Infrastructure/Persistence/AccountsManagerContext.cs",
                "region": {
                  "startLine": 24,
                  "startColumn": 32,
                  "endLine": 24,
                  "endColumn": 40
                }
              }
            }
          ],
          "properties": {
            "warningLevel": 1
          }
        },
        {
          "ruleId": "CS8618",
          "level": "warning",
          "message": "Non-nullable property 'Accounts' must contain a non-null value when exiting constructor. Consider declaring the property as nullable.",
          "locations": [
            {
              "resultFile": {
                "uri": "file:///Users/abdulhadi.elhussain/Projects/AbdulhadiNagarroAssignment/AbdulhadiNagarroAssignment.Infrastructure/Persistence/AccountsManagerContext.cs",
                "region": {
                  "startLine": 15,
                  "startColumn": 16,
                  "endLine": 15,
                  "endColumn": 38
                }
              }
            }
          ],
          "relatedLocations": [
            {
              "physicalLocation": {
                "uri": "file:///Users/abdulhadi.elhussain/Projects/AbdulhadiNagarroAssignment/AbdulhadiNagarroAssignment.Infrastructure/Persistence/AccountsManagerContext.cs",
                "region": {
                  "startLine": 19,
                  "startColumn": 31,
                  "endLine": 19,
                  "endColumn": 39
                }
              }
            }
          ],
          "properties": {
            "warningLevel": 1
          }
        },
        {
          "ruleId": "CS8618",
          "level": "warning",
          "message": "Non-nullable property 'Statements' must contain a non-null value when exiting constructor. Consider declaring the property as nullable.",
          "locations": [
            {
              "resultFile": {
                "uri": "file:///Users/abdulhadi.elhussain/Projects/AbdulhadiNagarroAssignment/AbdulhadiNagarroAssignment.Infrastructure/Persistence/AccountsManagerContext.cs",
                "region": {
                  "startLine": 15,
                  "startColumn": 16,
                  "endLine": 15,
                  "endColumn": 38
                }
              }
            }
          ],
          "relatedLocations": [
            {
              "physicalLocation": {
                "uri": "file:///Users/abdulhadi.elhussain/Projects/AbdulhadiNagarroAssignment/AbdulhadiNagarroAssignment.Infrastructure/Persistence/AccountsManagerContext.cs",
                "region": {
                  "startLine": 20,
                  "startColumn": 33,
                  "endLine": 20,
                  "endColumn": 43
                }
              }
            }
          ],
          "properties": {
            "warningLevel": 1
          }
        },
        {
          "ruleId": "CS8618",
          "level": "warning",
          "message": "Non-nullable property 'Roles' must contain a non-null value when exiting constructor. Consider declaring the property as nullable.",
          "locations": [
            {
              "resultFile": {
                "uri": "file:///Users/abdulhadi.elhussain/Projects/AbdulhadiNagarroAssignment/AbdulhadiNagarroAssignment.Infrastructure/Persistence/AccountsManagerContext.cs",
                "region": {
                  "startLine": 15,
                  "startColumn": 16,
                  "endLine": 15,
                  "endColumn": 38
                }
              }
            }
          ],
          "relatedLocations": [
            {
              "physicalLocation": {
                "uri": "file:///Users/abdulhadi.elhussain/Projects/AbdulhadiNagarroAssignment/AbdulhadiNagarroAssignment.Infrastructure/Persistence/AccountsManagerContext.cs",
                "region": {
                  "startLine": 21,
                  "startColumn": 29,
                  "endLine": 21,
                  "endColumn": 34
                }
              }
            }
          ],
          "properties": {
            "warningLevel": 1
          }
        },
        {
          "ruleId": "CS8618",
          "level": "warning",
          "message": "Non-nullable property 'Users' must contain a non-null value when exiting constructor. Consider declaring the property as nullable.",
          "locations": [
            {
              "resultFile": {
                "uri": "file:///Users/abdulhadi.elhussain/Projects/AbdulhadiNagarroAssignment/AbdulhadiNagarroAssignment.Infrastructure/Persistence/AccountsManagerContext.cs",
                "region": {
                  "startLine": 15,
                  "startColumn": 16,
                  "endLine": 15,
                  "endColumn": 38
                }
              }
            }
          ],
          "relatedLocations": [
            {
              "physicalLocation": {
                "uri": "file:///Users/abdulhadi.elhussain/Projects/AbdulhadiNagarroAssignment/AbdulhadiNagarroAssignment.Infrastructure/Persistence/AccountsManagerContext.cs",
                "region": {
                  "startLine": 22,
                  "startColumn": 29,
                  "endLine": 22,
                  "endColumn": 34
                }
              }
            }
          ],
          "properties": {
            "warningLevel": 1
          }
        },
        {
          "ruleId": "CS8618",
          "level": "warning",
          "message": "Non-nullable property 'UsersRoles' must contain a non-null value when exiting constructor. Consider declaring the property as nullable.",
          "locations": [
            {
              "resultFile": {
                "uri": "file:///Users/abdulhadi.elhussain/Projects/AbdulhadiNagarroAssignment/AbdulhadiNagarroAssignment.Infrastructure/Persistence/AccountsManagerContext.cs",
                "region": {
                  "startLine": 15,
                  "startColumn": 16,
                  "endLine": 15,
                  "endColumn": 38
                }
              }
            }
          ],
          "relatedLocations": [
            {
              "physicalLocation": {
                "uri": "file:///Users/abdulhadi.elhussain/Projects/AbdulhadiNagarroAssignment/AbdulhadiNagarroAssignment.Infrastructure/Persistence/AccountsManagerContext.cs",
                "region": {
                  "startLine": 23,
                  "startColumn": 33,
                  "endLine": 23,
                  "endColumn": 43
                }
              }
            }
          ],
          "properties": {
            "warningLevel": 1
          }
        },
        {
          "ruleId": "CS8618",
          "level": "warning",
          "message": "Non-nullable property 'Sessions' must contain a non-null value when exiting constructor. Consider declaring the property as nullable.",
          "locations": [
            {
              "resultFile": {
                "uri": "file:///Users/abdulhadi.elhussain/Projects/AbdulhadiNagarroAssignment/AbdulhadiNagarroAssignment.Infrastructure/Persistence/AccountsManagerContext.cs",
                "region": {
                  "startLine": 15,
                  "startColumn": 16,
                  "endLine": 15,
                  "endColumn": 38
                }
              }
            }
          ],
          "relatedLocations": [
            {
              "physicalLocation": {
                "uri": "file:///Users/abdulhadi.elhussain/Projects/AbdulhadiNagarroAssignment/AbdulhadiNagarroAssignment.Infrastructure/Persistence/AccountsManagerContext.cs",
                "region": {
                  "startLine": 24,
                  "startColumn": 32,
                  "endLine": 24,
                  "endColumn": 40
                }
              }
            }
          ],
          "properties": {
            "warningLevel": 1
          }
        },
        {
          "ruleId": "CS8603",
          "level": "warning",
          "message": "Possible null reference return.",
          "locations": [
            {
              "resultFile": {
                "uri": "file:///Users/abdulhadi.elhussain/Projects/AbdulhadiNagarroAssignment/AbdulhadiNagarroAssignment.Infrastructure/Persistence/Repositories/UserRepository.cs",
                "region": {
                  "startLine": 17,
                  "startColumn": 20,
                  "endLine": 17,
                  "endColumn": 33
                }
              }
            }
          ],
          "properties": {
            "warningLevel": 1
          }
        },
        {
          "ruleId": "CS8602",
          "level": "warning",
          "message": "Dereference of a possibly null reference.",
          "locations": [
            {
              "resultFile": {
                "uri": "file:///Users/abdulhadi.elhussain/Projects/AbdulhadiNagarroAssignment/AbdulhadiNagarroAssignment.Infrastructure/Persistence/Repositories/UserRepository.cs",
                "region": {
                  "startLine": 22,
                  "startColumn": 54,
                  "endLine": 22,
                  "endColumn": 55
                }
              }
            }
          ],
          "properties": {
            "warningLevel": 1
          }
        },
        {
          "ruleId": "CS8602",
          "level": "warning",
          "message": "Dereference of a possibly null reference.",
          "locations": [
            {
              "resultFile": {
                "uri": "file:///Users/abdulhadi.elhussain/Projects/AbdulhadiNagarroAssignment/AbdulhadiNagarroAssignment.Infrastructure/Persistence/Repositories/UserRepository.cs",
                "region": {
                  "startLine": 23,
                  "startColumn": 41,
                  "endLine": 23,
                  "endColumn": 42
                }
              }
            }
          ],
          "properties": {
            "warningLevel": 1
          }
        },
        {
          "ruleId": "CS8602",
          "level": "warning",
          "message": "Dereference of a possibly null reference.",
          "locations": [
            {
              "resultFile": {
                "uri": "file:///Users/abdulhadi.elhussain/Projects/AbdulhadiNagarroAssignment/AbdulhadiNagarroAssignment.Infrastructure/Persistence/Repositories/UserRepository.cs",
                "region": {
                  "startLine": 28,
                  "startColumn": 66,
                  "endLine": 28,
                  "endColumn": 67
                }
              }
            }
          ],
          "properties": {
            "warningLevel": 1
          }
        },
        {
          "ruleId": "S2068",
          "level": "warning",
          "message": "\"password\" detected here, make sure this is not a hard-coded credential.",
          "locations": [
            {
              "resultFile": {
                "uri": "file:///Users/abdulhadi.elhussain/Projects/AbdulhadiNagarroAssignment/AbdulhadiNagarroAssignment.Infrastructure/Persistence/AccountsManagerContextSeed.cs",
                "region": {
                  "startLine": 21,
                  "startColumn": 17,
                  "endLine": 21,
                  "endColumn": 35
                }
              }
            }
          ],
          "properties": {
            "warningLevel": 1
          }
        },
        {
          "ruleId": "S2068",
          "level": "warning",
          "message": "\"password\" detected here, make sure this is not a hard-coded credential.",
          "locations": [
            {
              "resultFile": {
                "uri": "file:///Users/abdulhadi.elhussain/Projects/AbdulhadiNagarroAssignment/AbdulhadiNagarroAssignment.Infrastructure/Persistence/AccountsManagerContextSeed.cs",
                "region": {
                  "startLine": 28,
                  "startColumn": 17,
                  "endLine": 28,
                  "endColumn": 34
                }
              }
            }
          ],
          "properties": {
            "warningLevel": 1
          }
        },
        {
          "ruleId": "S2068",
          "level": "warning",
          "message": "\"password\" detected here, make sure this is not a hard-coded credential.",
          "locations": [
            {
              "resultFile": {
                "uri": "file:///Users/abdulhadi.elhussain/Projects/AbdulhadiNagarroAssignment/AbdulhadiNagarroAssignment.Infrastructure/Persistence/AccountsManagerContextSeed.cs",
                "region": {
                  "startLine": 34,
                  "startColumn": 17,
                  "endLine": 34,
                  "endColumn": 34
                }
              }
            }
          ],
          "properties": {
            "warningLevel": 1
          }
        }
      ],
      "rules": {
        "CS8602": {
          "id": "CS8602",
          "shortDescription": "Dereference of a possibly null reference.",
          "defaultLevel": "warning",
          "helpUri": "https://msdn.microsoft.com/query/roslyn.query?appId=roslyn&k=k(CS8602)",
          "properties": {
            "category": "Compiler",
            "isEnabledByDefault": true,
            "tags": [
              "Compiler",
              "Telemetry"
            ]
          }
        },
        "CS8603": {
          "id": "CS8603",
          "shortDescription": "Possible null reference return.",
          "defaultLevel": "warning",
          "helpUri": "https://msdn.microsoft.com/query/roslyn.query?appId=roslyn&k=k(CS8603)",
          "properties": {
            "category": "Compiler",
            "isEnabledByDefault": true,
            "tags": [
              "Compiler",
              "Telemetry"
            ]
          }
        },
        "CS8613": {
          "id": "CS8613",
          "shortDescription": "Nullability of reference types in return type doesn't match implicitly implemented member.",
          "defaultLevel": "warning",
          "helpUri": "https://msdn.microsoft.com/query/roslyn.query?appId=roslyn&k=k(CS8613)",
          "properties": {
            "category": "Compiler",
            "isEnabledByDefault": true,
            "tags": [
              "Compiler",
              "Telemetry"
            ]
          }
        },
        "CS8618": {
          "id": "CS8618",
          "shortDescription": "Non-nullable field must contain a non-null value when exiting constructor. Consider declaring as nullable.",
          "defaultLevel": "warning",
          "helpUri": "https://msdn.microsoft.com/query/roslyn.query?appId=roslyn&k=k(CS8618)",
          "properties": {
            "category": "Compiler",
            "isEnabledByDefault": true,
            "tags": [
              "Compiler",
              "Telemetry"
            ]
          }
        },
        "CS8634": {
          "id": "CS8634",
          "shortDescription": "The type cannot be used as type parameter in the generic type or method. Nullability of type argument doesn't match 'class' constraint.",
          "defaultLevel": "warning",
          "helpUri": "https://msdn.microsoft.com/query/roslyn.query?appId=roslyn&k=k(CS8634)",
          "properties": {
            "category": "Compiler",
            "isEnabledByDefault": true,
            "tags": [
              "Compiler",
              "Telemetry"
            ]
          }
        },
        "S2068": {
          "id": "S2068",
          "shortDescription": "Hard-coded credentials are security-sensitive",
          "fullDescription": "Because it is easy to extract strings from an application source code or binary, credentials should not be hard-coded. This is particularly true for applications that are distributed or that are open-source.",
          "defaultLevel": "warning",
          "helpUri": "https://rules.sonarsource.com/csharp/RSPEC-2068",
          "properties": {
            "category": "Blocker Security Hotspot",
            "isEnabledByDefault": true,
            "tags": [
              "C#",
              "MainSourceScope",
              "SonarWay"
            ]
          }
        }
      }
    }
  ]
}